<annotation>
	<folder>Abrasions</folder>
	<filename>abrasions (29).jpg</filename>
	<path>D:\amien\Berkas Bangkit\capstone\dataset_luka\Wound_dataset\Abrasions\abrasions (29).jpg</path>
	<source>
		<database>Unknown</database>
	</source>
	<size>
		<width>640</width>
		<height>640</height>
		<depth>3</depth>
	</size>
	<segmented>0</segmented>
	<object>
		<name>Luka Lecet</name>
		<pose>Unspecified</pose>
		<truncated>0</truncated>
		<difficult>0</difficult>
		<bndbox>
			<xmin>230</xmin>
			<ymin>38</ymin>
			<xmax>410</xmax>
			<ymax>473</ymax>
		</bndbox>
	</object>
	<object>
		<name>Luka Lecet</name>
		<pose>Unspecified</pose>
		<truncated>0</truncated>
		<difficult>0</difficult>
		<bndbox>
			<xmin>163</xmin>
			<ymin>169</ymin>
			<xmax>276</xmax>
			<ymax>445</ymax>
		</bndbox>
	</object>
	<object>
		<name>Luka Lecet</name>
		<pose>Unspecified</pose>
		<truncated>0</truncated>
		<difficult>0</difficult>
		<bndbox>
			<xmin>275</xmin>
			<ymin>111</ymin>
			<xmax>394</xmax>
			<ymax>417</ymax>
		</bndbox>
	</object>
</annotation>
